LICENSE
MANIFEST.in
README.md
setup.cfg
setup.py
django_task_schedule.egg-info/PKG-INFO
django_task_schedule.egg-info/SOURCES.txt
django_task_schedule.egg-info/dependency_links.txt
django_task_schedule.egg-info/requires.txt
django_task_schedule.egg-info/top_level.txt
task_schedule/__init__.py
task_schedule/admin.py
task_schedule/apps.py
task_schedule/models.py
task_schedule/serializers.py
task_schedule/settings.py
task_schedule/urls.py
task_schedule/views.py
task_schedule/migrations/0001_initial.py
task_schedule/migrations/__init__.py
task_schedule/static/task_schedule/main.js
task_schedule/static/task_schedule/style.css
task_schedule/static/task_schedule/components/column-form.js
task_schedule/static/task_schedule/components/rules.js
task_schedule/static/task_schedule/components/schedule-form.js
task_schedule/static/task_schedule/components/task-form.js
task_schedule/static/task_schedule/views/index.js
task_schedule/static/task_schedule/views/page-not-found.js
task_schedule/static/task_schedule/views/schedule.js
task_schedule/templates/task_schedule/index.html