Metadata-Version: 1.1
Name: django-task-schedule
Version: 0.0.2
Summary: Task schedule grid app for Django
Home-page: UNKNOWN
Author: Mikhail Gavrin
Author-email: UNKNOWN
License: MIT
Platform: UNKNOWN
Classifier: Framework :: Django
